ruamel.bws-0.4.1-py3.9-nspkg.pth
ruamel/bws/__init__.py
ruamel/bws/__main__.py
ruamel/bws/browserworkspace.py
ruamel.bws-0.4.1.dist-info/LICENSE
ruamel.bws-0.4.1.dist-info/METADATA
ruamel.bws-0.4.1.dist-info/WHEEL
ruamel.bws-0.4.1.dist-info/entry_points.txt
ruamel.bws-0.4.1.dist-info/namespace_packages.txt
ruamel.bws-0.4.1.dist-info/top_level.txt
ruamel.bws-0.4.1.dist-info/RECORD
